[
  {
    "topic": "แก๊สและสมบัติของแก๊ส",
    "subtopic": "กฎของบอยล์ (P-V ที่อุณหภูมิคงที่)",
    "stem": "แก๊สชนิดหนึ่งมีปริมาตร 6.0 L ที่ความดัน 1.0 atm เมื่ออัดแก๊สนี้ที่อุณหภูมิคงที่จนความดันเป็น 2.5 atm แก๊สจะมีปริมาตรกี่ลิตร",
    "choices": [
      "15 L",
      "2.4 L",
      "0.42 L",
      "3.5 L"
    ],
    "correct_index": 1,
    "explanation": "**ขั้นที่ 1:** อุณหภูมิคงที่และจำนวนโมลคงที่ จึงใช้กฎของบอยล์ $P_1V_1 = P_2V_2$\n\n**ขั้นที่ 2:** แทนค่า\n\n$$V_2 = \\frac{P_1V_1}{P_2} = \\frac{1.0\\ \\cancel{\\text{atm}} \\times 6.0\\ \\text{L}}{2.5\\ \\cancel{\\text{atm}}} = 2.4\\ \\text{L}$$\n\n**ตรวจสอบเชิงเหตุผล:** ความดันเพิ่มขึ้น ปริมาตรต้องลดลง (แปรผกผันกัน) คำตอบ 2.4 L < 6.0 L สมเหตุสมผล\n\n*ข้อควรระวัง:* ถ้าเผลอคูณ $6.0 \\times 2.5 = 15$ จะได้ตัวลวง 15 L ซึ่งขัดกับหลักที่ว่าอัดแก๊สแล้วปริมาตรต้องเล็กลง",
    "difficulty": 1
  },
  {
    "topic": "แก๊สและสมบัติของแก๊ส",
    "subtopic": "กฎแก๊สเดี่ยว (บอยล์ ชาร์ล เกย์-ลูสแซก)",
    "stem": "แก๊สปริมาตร 400 mL ที่อุณหภูมิ 27 °C เมื่อให้ความร้อนจนอุณหภูมิเป็น 127 °C โดยความดันคงที่ แก๊สจะมีปริมาตรประมาณกี่มิลลิลิตร",
    "choices": [
      "1881 mL",
      "300 mL",
      "533 mL",
      "400 mL"
    ],
    "correct_index": 2,
    "explanation": "**ขั้นที่ 1:** ความดันคงที่ ใช้กฎของชาร์ล $\\frac{V_1}{T_1} = \\frac{V_2}{T_2}$ โดยอุณหภูมิ **ต้องเป็นเคลวินเสมอ**\n\n$$T_1 = 27 + 273 = 300\\ \\text{K}, \\quad T_2 = 127 + 273 = 400\\ \\text{K}$$\n\n**ขั้นที่ 2:** แทนค่า\n\n$$V_2 = V_1 \\times \\frac{T_2}{T_1} = 400\\ \\text{mL} \\times \\frac{400\\ \\cancel{\\text{K}}}{300\\ \\cancel{\\text{K}}} \\approx 533\\ \\text{mL}$$\n\n**ข้อควรระวัง:** ถ้าใช้องศาเซลเซียสโดยตรง $400 \\times \\frac{127}{27} \\approx 1881$ mL จะผิดทันที เพราะกฎของแก๊สทุกกฎอ้างอิงอุณหภูมิสัมบูรณ์ (K) เท่านั้น และถ้าสลับเศษส่วนเป็น $\\frac{300}{400}$ จะได้ 300 mL ซึ่งขัดกับความจริงที่ว่าให้ความร้อนแล้วแก๊สต้องขยายตัว",
    "difficulty": 2
  },
  {
    "topic": "แก๊สและสมบัติของแก๊ส",
    "subtopic": "กฎแก๊สเดี่ยว (บอยล์ ชาร์ล เกย์-ลูสแซก)",
    "stem": "ถังเหล็กปิดสนิท (ปริมาตรคงที่) บรรจุแก๊สความดัน 1.5 atm ที่ 27 °C ถ้าถังนี้ทนความดันได้สูงสุด 3.0 atm จะต้องให้ความร้อนจนอุณหภูมิถึงกี่องศาเซลเซียสถังจึงจะเริ่มระเบิด",
    "choices": [
      "327 °C",
      "600 °C",
      "54 °C",
      "573 °C"
    ],
    "correct_index": 0,
    "explanation": "**ขั้นที่ 1:** ปริมาตรคงที่ ใช้กฎของเกย์-ลูสแซก $\\frac{P_1}{T_1} = \\frac{P_2}{T_2}$\n\n$$T_1 = 27 + 273 = 300\\ \\text{K}$$\n\n**ขั้นที่ 2:** หาอุณหภูมิที่ความดันถึง 3.0 atm\n\n$$T_2 = T_1 \\times \\frac{P_2}{P_1} = 300\\ \\text{K} \\times \\frac{3.0\\ \\cancel{\\text{atm}}}{1.5\\ \\cancel{\\text{atm}}} = 600\\ \\text{K}$$\n\n**ขั้นที่ 3:** โจทย์ถามเป็นองศาเซลเซียส ต้องแปลงกลับ\n\n$$600 - 273 = 327\\ ^{\\circ}\\text{C}$$\n\n**ข้อควรระวัง:** ตัวลวง 600 °C คือลืมแปลง K กลับเป็น °C ส่วน 54 °C มาจากการคิดผิดว่าความดันเพิ่ม 2 เท่า อุณหภูมิเซลเซียสก็เพิ่ม 2 เท่า ($27 \\times 2$) ซึ่งใช้ไม่ได้เพราะสัดส่วนตรงใช้ได้กับเคลวินเท่านั้น",
    "difficulty": 3
  },
  {
    "topic": "แก๊สและสมบัติของแก๊ส",
    "subtopic": "กฎแก๊สรวมและ PV=nRT",
    "stem": "แก๊สจำนวนหนึ่งมีปริมาตร 3.0 L ที่ความดัน 1.2 atm อุณหภูมิ 27 °C เมื่อเปลี่ยนสภาวะเป็นความดัน 0.9 atm อุณหภูมิ 127 °C แก๊สจะมีปริมาตรประมาณกี่ลิตร",
    "choices": [
      "3.00 L",
      "1.69 L",
      "18.8 L",
      "5.33 L"
    ],
    "correct_index": 3,
    "explanation": "**ขั้นที่ 1:** ทั้งความดันและอุณหภูมิเปลี่ยน ใช้กฎรวมแก๊ส $\\frac{P_1V_1}{T_1} = \\frac{P_2V_2}{T_2}$\n\n$$T_1 = 300\\ \\text{K}, \\quad T_2 = 400\\ \\text{K}$$\n\n**ขั้นที่ 2:** จัดรูปแล้วแทนค่า\n\n$$V_2 = V_1 \\times \\frac{P_1}{P_2} \\times \\frac{T_2}{T_1} = 3.0\\ \\text{L} \\times \\frac{1.2\\ \\cancel{\\text{atm}}}{0.9\\ \\cancel{\\text{atm}}} \\times \\frac{400\\ \\cancel{\\text{K}}}{300\\ \\cancel{\\text{K}}}$$\n\n$$V_2 = 3.0 \\times \\frac{4}{3} \\times \\frac{4}{3} \\approx 5.33\\ \\text{L}$$\n\n**ตรวจสอบเชิงเหตุผล:** ความดันลดลง (แก๊สขยาย) และอุณหภูมิสูงขึ้น (แก๊สขยาย) สองผลเสริมกัน ปริมาตรจึงต้องมากกว่า 3.0 L\n\n**ข้อควรระวัง:** ถ้าใส่อัตราส่วนความดันกลับด้าน $\\frac{0.9}{1.2}$ จะได้ 3.00 L พอดี (ดูเหมือนไม่เปลี่ยน) และถ้าใช้เซลเซียส $\\frac{127}{27}$ จะได้ 18.8 L",
    "difficulty": 3
  },
  {
    "topic": "แก๊สและสมบัติของแก๊ส",
    "subtopic": "กฎแก๊สรวมและ PV=nRT",
    "stem": "แก๊สชนิดหนึ่งมวล 0.80 g มีปริมาตร 0.492 L ที่ความดัน 1.0 atm อุณหภูมิ 27 °C มวลโมลาร์ของแก๊สนี้มีค่าประมาณกี่กรัมต่อโมล (กำหนด R = 0.0821 L·atm/(mol·K))",
    "choices": [
      "36 g/mol",
      "3.6 g/mol",
      "40 g/mol",
      "20 g/mol"
    ],
    "correct_index": 2,
    "explanation": "**ขั้นที่ 1:** จากกฎแก๊สอุดมคติ $PV = nRT$ และ $n = \\frac{m}{M}$ จัดรูปได้\n\n$$M = \\frac{mRT}{PV}$$\n\n**ขั้นที่ 2:** แปลงอุณหภูมิ $T = 27 + 273 = 300\\ \\text{K}$ แล้วแทนค่า\n\n$$M = \\frac{0.80\\ \\text{g} \\times 0.0821\\ \\frac{\\cancel{\\text{L}} \\cdot \\cancel{\\text{atm}}}{\\text{mol} \\cdot \\cancel{\\text{K}}} \\times 300\\ \\cancel{\\text{K}}}{1.0\\ \\cancel{\\text{atm}} \\times 0.492\\ \\cancel{\\text{L}}}$$\n\n$$M = \\frac{0.80 \\times 24.63}{0.492} \\approx 40\\ \\text{g/mol}$$\n\n(อาจตรวจสอบอีกทาง: $n = \\frac{PV}{RT} = \\frac{1.0 \\times 0.492}{24.63} \\approx 0.020\\ \\text{mol}$ ดังนั้น $M = \\frac{0.80}{0.020} = 40$)\n\n**ข้อควรระวัง:** ถ้าใช้ $T = 273\\ \\text{K}$ (จำสับสนกับ STP) จะได้ประมาณ 36 g/mol และถ้าลืมแปลงเป็นเคลวินโดยใช้ $T = 27$ จะได้ 3.6 g/mol",
    "difficulty": 3
  },
  {
    "topic": "แก๊สและสมบัติของแก๊ส",
    "subtopic": "กฎแก๊สรวมและ PV=nRT",
    "stem": "ความหนาแน่นของแก๊สคาร์บอนไดออกไซด์ ($\\mathrm{CO_2}$) ที่ความดัน 2.0 atm อุณหภูมิ 27 °C มีค่าประมาณกี่กรัมต่อลิตร (กำหนด C = 12, O = 16, R = 0.0821 L·atm/(mol·K))",
    "choices": [
      "1.96 g/L",
      "3.57 g/L",
      "1.79 g/L",
      "7.15 g/L"
    ],
    "correct_index": 1,
    "explanation": "**ขั้นที่ 1:** หามวลโมลาร์ของ $\\mathrm{CO_2}$\n\n$$M = 12 + (2 \\times 16) = 44\\ \\text{g/mol}$$\n\n**ขั้นที่ 2:** จาก $PV = nRT = \\frac{m}{M}RT$ จัดรูปเป็นสูตรความหนาแน่น\n\n$$d = \\frac{m}{V} = \\frac{PM}{RT}$$\n\n**ขั้นที่ 3:** แทนค่า ($T = 300\\ \\text{K}$)\n\n$$d = \\frac{2.0\\ \\text{atm} \\times 44\\ \\text{g/mol}}{0.0821\\ \\frac{\\text{L} \\cdot \\text{atm}}{\\text{mol} \\cdot \\text{K}} \\times 300\\ \\text{K}} = \\frac{88}{24.63} \\approx 3.57\\ \\text{g/L}$$\n\n**ข้อควรระวัง:** ตัวลวง 1.96 g/L มาจากการเผลอใช้สูตร STP คือ $\\frac{44}{22.4}$ ทั้งที่สภาวะนี้ไม่ใช่ STP (ความดัน 2.0 atm และอุณหภูมิ 27 °C) ส่วน 1.79 g/L คือลืมคูณความดัน 2.0 atm",
    "difficulty": 3
  },
  {
    "topic": "แก๊สและสมบัติของแก๊ส",
    "subtopic": "ความดันย่อยและแก๊สผสม",
    "stem": "บรรจุแก๊ส $\\mathrm{CH_4}$ 8 g และแก๊ส $\\mathrm{O_2}$ 8 g ในถังใบเดียวกันโดยไม่เกิดปฏิกิริยา วัดความดันรวมได้ 1.2 atm ความดันย่อยของแก๊ส $\\mathrm{O_2}$ เท่ากับกี่ atm (กำหนด H = 1, C = 12, O = 16)",
    "choices": [
      "0.3 atm",
      "0.6 atm",
      "0.8 atm",
      "0.4 atm"
    ],
    "correct_index": 3,
    "explanation": "**ขั้นที่ 1:** เปลี่ยนมวลเป็นโมลก่อนเสมอ (ความดันย่อยขึ้นกับ **เศษส่วนโมล** ไม่ใช่เศษส่วนมวล)\n\n$$n_{\\mathrm{CH_4}} = 8\\ \\cancel{\\text{g}} \\times \\frac{1\\ \\text{mol}}{16\\ \\cancel{\\text{g}}} = 0.50\\ \\text{mol}$$\n\n$$n_{\\mathrm{O_2}} = 8\\ \\cancel{\\text{g}} \\times \\frac{1\\ \\text{mol}}{32\\ \\cancel{\\text{g}}} = 0.25\\ \\text{mol}$$\n\n**ขั้นที่ 2:** หาเศษส่วนโมลของ $\\mathrm{O_2}$\n\n$$X_{\\mathrm{O_2}} = \\frac{0.25}{0.50 + 0.25} = \\frac{1}{3}$$\n\n**ขั้นที่ 3:** ใช้กฎความดันย่อยของดอลตัน\n\n$$P_{\\mathrm{O_2}} = X_{\\mathrm{O_2}} \\times P_{total} = \\frac{1}{3} \\times 1.2\\ \\text{atm} = 0.4\\ \\text{atm}$$\n\n**ข้อควรระวัง:** ถ้าใช้เศษส่วนมวล $\\frac{8}{16} \\times 1.2$ จะได้ตัวลวง 0.6 atm ส่วน 0.8 atm คือความดันย่อยของ $\\mathrm{CH_4}$ (ตอบผิดตัว)",
    "difficulty": 3
  },
  {
    "topic": "แก๊สและสมบัติของแก๊ส",
    "subtopic": "ความดันย่อยและแก๊สผสม",
    "stem": "เก็บแก๊ส $\\mathrm{O_2}$ ด้วยวิธีแทนที่น้ำ ได้แก๊สปริมาตร 500 mL ที่ 27 °C ความดันบรรยากาศ 760 mmHg กำหนดความดันไอของน้ำที่ 27 °C = 27 mmHg แก๊ส $\\mathrm{O_2}$ แห้งนี้จะมีปริมาตรประมาณกี่มิลลิลิตรที่ STP (0 °C, 760 mmHg)",
    "choices": [
      "439 mL",
      "455 mL",
      "482 mL",
      "530 mL"
    ],
    "correct_index": 0,
    "explanation": "**ขั้นที่ 1:** แก๊สที่เก็บเหนือน้ำเป็นแก๊สผสมระหว่าง $\\mathrm{O_2}$ กับไอน้ำ ใช้กฎของดอลตันหาความดันย่อยของ $\\mathrm{O_2}$ แห้ง\n\n$$P_{\\mathrm{O_2}} = P_{atm} - P_{\\mathrm{H_2O}} = 760 - 27 = 733\\ \\text{mmHg}$$\n\n**ขั้นที่ 2:** ใช้กฎรวมแก๊สแปลงไปที่ STP โดย $T_1 = 300\\ \\text{K}$, $T_2 = 273\\ \\text{K}$, $P_2 = 760\\ \\text{mmHg}$\n\n$$V_2 = V_1 \\times \\frac{P_1}{P_2} \\times \\frac{T_2}{T_1} = 500\\ \\text{mL} \\times \\frac{733\\ \\cancel{\\text{mmHg}}}{760\\ \\cancel{\\text{mmHg}}} \\times \\frac{273\\ \\cancel{\\text{K}}}{300\\ \\cancel{\\text{K}}}$$\n\n$$V_2 = 500 \\times 0.9645 \\times 0.91 \\approx 439\\ \\text{mL}$$\n\n**ตรวจสอบเชิงเหตุผล:** ทั้งการหักไอน้ำ (ความดันแก๊สจริงน้อยลง) และการลดอุณหภูมิ ล้วนทำให้ปริมาตรเล็กลง คำตอบจึงต้องน้อยกว่า 500 mL\n\n**ข้อควรระวัง:** ถ้าลืมหักความดันไอน้ำจะได้ 455 mL ถ้าลืมปรับอุณหภูมิจะได้ 482 mL และถ้ากลับอัตราส่วนอุณหภูมิเป็น $\\frac{300}{273}$ จะได้ 530 mL",
    "difficulty": 4
  },
  {
    "topic": "แก๊สและสมบัติของแก๊ส",
    "subtopic": "ทฤษฎีจลน์ของแก๊สและการแพร่ (เกรแฮม)",
    "stem": "แก๊ส $\\mathrm{O_2}$ ปริมาตรหนึ่งแพร่ผ่านรูพรุนเล็ก ๆ จนหมดใช้เวลา 50 วินาที ถ้าแก๊ส X ปริมาตรเท่ากัน ที่อุณหภูมิและความดันเดียวกัน ใช้เวลา 100 วินาที มวลโมลาร์ของแก๊ส X เท่ากับกี่กรัมต่อโมล (กำหนด O = 16)",
    "choices": [
      "64 g/mol",
      "16 g/mol",
      "128 g/mol",
      "8 g/mol"
    ],
    "correct_index": 2,
    "explanation": "**ขั้นที่ 1:** กฎการแพร่ของแกรห์ม: อัตราการแพร่แปรผกผันกับรากที่สองของมวลโมลาร์ และเนื่องจากปริมาตรเท่ากัน **เวลา** จึงแปรผกผันกับอัตรา\n\n$$\\frac{r_{\\mathrm{O_2}}}{r_{X}} = \\frac{t_{X}}{t_{\\mathrm{O_2}}} = \\sqrt{\\frac{M_{X}}{M_{\\mathrm{O_2}}}}$$\n\n**ขั้นที่ 2:** แทนค่า ($M_{\\mathrm{O_2}} = 32$)\n\n$$\\frac{100\\ \\cancel{\\text{s}}}{50\\ \\cancel{\\text{s}}} = \\sqrt{\\frac{M_{X}}{32}}$$\n\n**ขั้นที่ 3:** ยกกำลังสองทั้งสองข้าง\n\n$$2^2 = \\frac{M_{X}}{32} \\quad \\to \\quad M_{X} = 4 \\times 32 = 128\\ \\text{g/mol}$$\n\n**ตรวจสอบเชิงเหตุผล:** แก๊ส X ใช้เวลานานกว่า แสดงว่าแพร่ช้ากว่า จึงต้องหนักกว่า $\\mathrm{O_2}$\n\n**ข้อควรระวัง:** ตัวลวง 64 คือคิดแบบเส้นตรง (เวลา 2 เท่า มวล 2 เท่า) โดยลืมยกกำลังสอง ส่วน 8 คือจับอัตราส่วนกลับด้าน ($32 \\div 4$) ซึ่งขัดแย้งกับข้อเท็จจริงที่ว่าแก๊สที่แพร่ช้ากว่าต้องหนักกว่า",
    "difficulty": 3
  },
  {
    "topic": "แก๊สและสมบัติของแก๊ส",
    "subtopic": "ทฤษฎีจลน์ของแก๊สและการแพร่ (เกรแฮม)",
    "stem": "แก๊สจริงมีพฤติกรรมเบี่ยงเบนไปจากแก๊สอุดมคติมากที่สุดที่สภาวะใด",
    "choices": [
      "ความดันต่ำ อุณหภูมิสูง",
      "ความดันสูง อุณหภูมิต่ำ",
      "ความดันต่ำ อุณหภูมิต่ำ",
      "ความดันสูง อุณหภูมิสูง"
    ],
    "correct_index": 1,
    "explanation": "**หลักคิดจากทฤษฎีจลน์ของแก๊ส** แก๊สอุดมคติตั้งอยู่บนข้อสมมติสำคัญ 2 ข้อ ได้แก่\n\n1. ปริมาตรของโมเลกุลน้อยมากจนตัดทิ้งได้เมื่อเทียบกับปริมาตรภาชนะ\n2. ไม่มีแรงยึดเหนี่ยวระหว่างโมเลกุล\n\n**พิจารณาทีละเงื่อนไข**\n\n- ที่ **ความดันสูง** โมเลกุลถูกอัดจนอยู่ชิดกันมาก ปริมาตรของตัวโมเลกุลเองเริ่มมีนัยสำคัญเมื่อเทียบกับปริมาตรภาชนะ ข้อสมมติข้อ 1 จึงใช้ไม่ได้\n- ที่ **อุณหภูมิต่ำ** โมเลกุลเคลื่อนที่ช้า พลังงานจลน์ต่ำจนแรงดึงดูดระหว่างโมเลกุลเริ่มมีผลชัดเจน ข้อสมมติข้อ 2 จึงใช้ไม่ได้ (และหากต่ำมากพอ แก๊สจะควบแน่นเป็นของเหลว)\n\nดังนั้นสภาวะ **ความดันสูงและอุณหภูมิต่ำ** ทำให้แก๊สจริงเบี่ยงเบนจากกฎ $PV = nRT$ มากที่สุด\n\nในทางกลับกัน ที่ความดันต่ำและอุณหภูมิสูง โมเลกุลอยู่ห่างกันและเคลื่อนที่เร็ว แก๊สจริงจึงมีพฤติกรรมเข้าใกล้แก๊สอุดมคติมากที่สุด",
    "difficulty": 2
  },
  {
    "topic": "แก๊สและสมบัติของแก๊ส",
    "subtopic": "ปริมาณสัมพันธ์ของแก๊สในปฏิกิริยา",
    "stem": "จุดประกายไฟให้แก๊ส $\\mathrm{H_2}$ 4 g ทำปฏิกิริยากับแก๊ส $\\mathrm{O_2}$ 16 g จนสมบูรณ์ตามสมการ $2\\mathrm{H_2(g)} + \\mathrm{O_2(g)} \\rightarrow 2\\mathrm{H_2O(l)}$ เมื่อปฏิกิริยาสิ้นสุดและวัดที่ STP แก๊สที่เหลืออยู่จะมีปริมาตรกี่ลิตร (กำหนด H = 1, O = 16, ที่ STP แก๊ส 1 โมล = 22.4 L)",
    "choices": [
      "11.2 L",
      "44.8 L",
      "33.6 L",
      "22.4 L"
    ],
    "correct_index": 3,
    "explanation": "**ขั้นที่ 1:** เปลี่ยนมวลเป็นโมล\n\n$$n_{\\mathrm{H_2}} = 4\\ \\cancel{\\text{g}} \\times \\frac{1\\ \\text{mol}}{2\\ \\cancel{\\text{g}}} = 2.0\\ \\text{mol}$$\n\n$$n_{\\mathrm{O_2}} = 16\\ \\cancel{\\text{g}} \\times \\frac{1\\ \\text{mol}}{32\\ \\cancel{\\text{g}}} = 0.5\\ \\text{mol}$$\n\n**ขั้นที่ 2:** หาสารกำหนดปริมาณ จากสมการ $\\mathrm{H_2} : \\mathrm{O_2} = 2 : 1$ ดังนั้น $\\mathrm{O_2}$ 0.5 mol ต้องใช้ $\\mathrm{H_2}$ เพียง $2 \\times 0.5 = 1.0$ mol แต่มี $\\mathrm{H_2}$ ถึง 2.0 mol แสดงว่า $\\mathrm{O_2}$ หมดก่อน (เป็นสารกำหนดปริมาณ)\n\n**ขั้นที่ 3:** หาแก๊สที่เหลือ — น้ำที่เกิดขึ้นเป็นของเหลวที่ STP จึงเหลือเฉพาะ $\\mathrm{H_2}$\n\n$$n_{\\mathrm{H_2}}\\ \\text{(left)} = 2.0 - 1.0 = 1.0\\ \\text{mol}$$\n\n**ขั้นที่ 4:** คิดเป็นปริมาตรที่ STP\n\n$$V = 1.0\\ \\cancel{\\text{mol}} \\times 22.4\\ \\frac{\\text{L}}{\\cancel{\\text{mol}}} = 22.4\\ \\text{L}$$\n\n**ข้อควรระวัง:** ตัวลวง 44.8 L คือลืมว่าปฏิกิริยาใช้ $\\mathrm{H_2}$ ไปแล้ว ส่วน 33.6 L มาจากการลบโมลตรง ๆ ($2.0 - 0.5 = 1.5$ mol) โดยไม่ดูอัตราส่วนในสมการ และ 11.2 L คือเข้าใจผิดว่า $\\mathrm{H_2}$ เป็นสารกำหนดปริมาณ",
    "difficulty": 4
  },
  {
    "topic": "แก๊สและสมบัติของแก๊ส",
    "subtopic": "ปริมาณสัมพันธ์ของแก๊สในปฏิกิริยา",
    "stem": "แก๊สผสมระหว่าง $\\mathrm{CH_4}$ และ $\\mathrm{C_2H_6}$ มีปริมาตรรวม 20 cm³ เมื่อเผาไหม้อย่างสมบูรณ์กับแก๊ส $\\mathrm{O_2}$ ที่มากเกินพอ เกิดแก๊ส $\\mathrm{CO_2}$ ปริมาตร 32 cm³ โดยปริมาตรทั้งหมดวัดที่อุณหภูมิและความดันเดียวกัน ร้อยละโดยปริมาตรของ $\\mathrm{CH_4}$ ในแก๊สผสมคือข้อใด",
    "choices": [
      "40%",
      "60%",
      "20%",
      "80%"
    ],
    "correct_index": 0,
    "explanation": "**หลักคิด:** ที่อุณหภูมิและความดันเดียวกัน อัตราส่วนปริมาตรของแก๊สเท่ากับอัตราส่วนโมล (กฎของอาโวกาโดร) จึงเทียบปริมาตรตามสมการเคมีได้โดยตรง\n\n**ขั้นที่ 1:** เขียนสมการเผาไหม้ทั้งสอง\n\n$$\\mathrm{CH_4} + 2\\mathrm{O_2} \\rightarrow \\mathrm{CO_2} + 2\\mathrm{H_2O}$$\n\n$$\\mathrm{C_2H_6} + \\frac{7}{2}\\mathrm{O_2} \\rightarrow 2\\mathrm{CO_2} + 3\\mathrm{H_2O}$$\n\nสังเกตว่า $\\mathrm{CH_4}$ 1 ปริมาตรให้ $\\mathrm{CO_2}$ 1 ปริมาตร แต่ $\\mathrm{C_2H_6}$ 1 ปริมาตรให้ $\\mathrm{CO_2}$ 2 ปริมาตร (ตามจำนวนอะตอม C)\n\n**ขั้นที่ 2:** ตั้งระบบสมการ ให้ปริมาตร $\\mathrm{CH_4} = x$ และ $\\mathrm{C_2H_6} = y$ (หน่วย cm³)\n\n$$x + y = 20$$\n\n$$x + 2y = 32$$\n\n**ขั้นที่ 3:** ลบสมการแรกออกจากสมการที่สอง\n\n$$y = 12 \\quad \\to \\quad x = 20 - 12 = 8$$\n\n**ขั้นที่ 4:** ตรวจสอบ: $\\mathrm{CO_2} = 8 + (2 \\times 12) = 32$ cm³ ตรงตามโจทย์\n\n$$\\%\\mathrm{CH_4} = \\frac{8}{20} \\times 100 = 40\\%$$\n\n**ข้อควรระวัง:** ตัวลวง 60% คือเผลอตอบร้อยละของ $\\mathrm{C_2H_6}$ (อ่านโจทย์ไม่ครบ) และผู้ที่ลืมคูณ 2 ให้ $\\mathrm{C_2H_6}$ ตามจำนวนอะตอมคาร์บอน จะตั้งสมการไม่ได้เลยเพราะจะได้ปริมาตร $\\mathrm{CO_2}$ เพียง 20 cm³ ไม่ถึง 32 cm³",
    "difficulty": 5
  }
]
